[
    {
        "name": "专区页管理",
        "index": "1-0",
        "icon": "system",
        "children": [
            {
                "index": "1-1",
                "name": "banner管理",
                "icon": "shuffling-banner",
                "path": "/index/prefecture/banner_manage"
            },
            {
                "index": "1-2",
                "name": "游戏特权管理",
                "icon": "game",
                "path": "/index/prefecture/game_privilege"
            },
            {
                "index": "1-3",
                "name": "服务特权管理",
                "icon": "server",
                "path": "/index/prefecture/server_privilege"
            },
            {
                "index": "1-4",
                "name": "资讯中心管理",
                "icon": "info",
                "path": "/index/prefecture/info_center"
            },
            {
                "index": "1-5",
                "name": "会员体系管理",
                "icon": "vip",
                "path": "/index/prefecture/vip_system"
            },
            {
                "index": "1-6",
                "name": "快速入口管理",
                "icon": "portal",
                "path": "/index/prefecture/portal"
            }
        ]
    },
    {
        "name": "账号信息管理",
        "index": "3-0",
        "icon": "account_manage",
        "children": [
            {
                "index": "3-1",
                "name": "登录管理",
                "icon": "personal",
                "path": "/index/account_manage/login_manage"
            },
            {
                "index": "3-2",
                "name": "个人中心",
                "icon": "user",
                "path": "/index/account_manage/personal_centre"
            }
        ]
    },
    {
        "name": "系统管理",
        "index": "2-0",
        "icon": "system",
        "children": [
            {
                "index": "2-1",
                "name": "用户管理",
                "icon": "user",
                "path": "/index/system/user_manage"
            }
        ]
    }
]
